googletrans/__init__.py
googletrans/client.py
googletrans/constants.py
googletrans/gtoken.py
googletrans/models.py
googletrans/urls.py
googletrans/utils.py
googletrans-4.0.1.dist-info/METADATA
googletrans-4.0.1.dist-info/WHEEL
googletrans-4.0.1.dist-info/entry_points.txt
googletrans-4.0.1.dist-info/licenses/LICENSE
googletrans-4.0.1.dist-info/RECORD
